README.md
setup.cfg
setup.py
KongFuPanda/__init__.py
KongFuPanda.egg-info/PKG-INFO
KongFuPanda.egg-info/SOURCES.txt
KongFuPanda.egg-info/dependency_links.txt
KongFuPanda.egg-info/requires.txt
KongFuPanda.egg-info/top_level.txt
KongFuPanda.egg-info/zip-safe
KongFuPanda/Classification/__init__.py
KongFuPanda/Classification/AdaBoost/__init__.py
KongFuPanda/Classification/KNN/KNN.py
KongFuPanda/Classification/KNN/__init__.py
KongFuPanda/Classification/Logistic/Logistic.py
KongFuPanda/Classification/Logistic/__init__.py
KongFuPanda/Classification/NaiveBayes/Byte.py
KongFuPanda/Classification/NaiveBayes/__init__.py
KongFuPanda/Classification/NeverRepeat/NR.py
KongFuPanda/Classification/NeverRepeat/__init__.py
KongFuPanda/Classification/SVM/__init__.py
KongFuPanda/Classification/Tree/Tree.py
KongFuPanda/Classification/Tree/TreePlotter.py
KongFuPanda/Classification/Tree/__init__.py
KongFuPanda/Classification/Tree/kk.py
KongFuPanda/Regression/__init__.py
KongFuPanda/Regression/GeneralRegession/__init__.py
KongFuPanda/Regression/TreeGegression/__init__.py
KongFuPanda/UnsupervisedLearning/__init__.py
KongFuPanda/UnsupervisedLearning/Apriori/__init__.py
KongFuPanda/UnsupervisedLearning/FP-growth/__init__.py
KongFuPanda/UnsupervisedLearning/K-means/__init__.py
KongFuPanda/Utils/StringUtils.py
KongFuPanda/Utils/__init__.py
KongFuPanda/test/Test.py
KongFuPanda/test/__init__.py
KongFuPanda/test/Logistic/LogisticTest.py
KongFuPanda/test/Logistic/__init__.py
KongFuPanda/test/Native/MailFiltering.py
KongFuPanda/test/Native/NativeTest.py
KongFuPanda/test/Native/Rss.py
KongFuPanda/test/Native/__init__.py
KongFuPanda/test/knn/DistinguishKNN.py
KongFuPanda/test/knn/__init__.py
KongFuPanda/test/knn/appointment/AppointmentKNN.py
KongFuPanda/test/knn/appointment/__init__.py
KongFuPanda/test/tree/Lenses.py
KongFuPanda/test/tree/TreeTest.py
KongFuPanda/test/tree/__init__.py