Metadata-Version: 1.2
Name: KongFuPanda
Version: 1.0.0
Summary: Framework for Advanced Statistics and Data Sciences
Home-page: https://github.com/KongFuPanda/MachineLearning.git
Author: luoaijun
Author-email: aijun.luo@outlook.com
Maintainer: luoaijun
Maintainer-email: aijun.luo@outlook.com
License: UNKNOWN
Project-URL: github.io, https://luoaijun.github.io/self
Keywords: knn ml svm tree NaiveBayes AdbBoost
Platform: UNKNOWN
Classifier: Development Status :: 5 - Production/Stable
Classifier: Intended Audience :: Developers
Classifier: Topic :: Software Development :: Code Generators
Classifier: License :: OSI Approved :: MIT License
Classifier: Programming Language :: Python :: 3
Classifier: Programming Language :: Python :: 3.4
Classifier: Programming Language :: Python :: 3.5
Classifier: Programming Language :: Python :: 3.6
Classifier: Programming Language :: Python :: 3.7
